macmouse/__init__.py
macmouse/__main__.py
macmouse/_darwinmouse.py
macmouse/_generic.py
macmouse/_mouse_event.py
macmouse/_mouse_tests.py
macmouse/_nixcommon.py
macmouse/_nixmouse.py
macmouse/_winmouse.py
macmouse-0.7.4.dist-info/LICENSE.txt
macmouse-0.7.4.dist-info/METADATA
macmouse-0.7.4.dist-info/WHEEL
macmouse-0.7.4.dist-info/top_level.txt
macmouse-0.7.4.dist-info/RECORD
