Metadata-Version: 2.1
Name: macmouse
Version: 0.7.4
Summary: Hook and simulate mouse events on Windows and Linux
Home-page: https://github.com/gansel51/mouse
Author: gansel51
Author-email: griffin.ansel@gmail.com
License: MIT
Keywords: mouse hook simulate hotkey
Platform: UNKNOWN
Classifier: Development Status :: 4 - Beta
Classifier: License :: OSI Approved :: MIT License
Classifier: Operating System :: MacOS
Classifier: Programming Language :: Python :: 2
Classifier: Programming Language :: Python :: 3
Classifier: Topic :: Software Development :: Libraries :: Python Modules
Classifier: Topic :: Utilities
